README.rst
setup.py
httpdec/__init__.py
httpdec/decode.py
httpdec/main.py
httpdec.egg-info/PKG-INFO
httpdec.egg-info/SOURCES.txt
httpdec.egg-info/dependency_links.txt
httpdec.egg-info/entry_points.txt
httpdec.egg-info/requires.txt
httpdec.egg-info/top_level.txt