Metadata-Version: 1.0
Name: httpdec
Version: 0.0.4
Summary: a tool can decode http headers/cookies/...
Home-page: https://github.com/alingse/httpdec
Author: alingse
Author-email: alingse@foxmail.com
License: Apache 2.0
Platform: UNKNOWN
